algox/__init__.py
algox/helpers.py
algox/search.py
algox/sort.py
algox/ds/__init__.py
algox/ds/linkedlist.py
algox/ds/stack.py
algox-0.1.0.dist-info/METADATA
algox-0.1.0.dist-info/WHEEL
algox-0.1.0.dist-info/top_level.txt
algox-0.1.0.dist-info/RECORD
