Metadata-Version: 2.4
Name: algox
Version: 0.1.0
Summary: A collection of data structures and algorithms, all implemented in pure Python
Author: Prasad Raju G
Requires-Python: >=3.13
Provides-Extra: perf
Requires-Dist: matplotlib>=3.10.8; extra == "perf"
